gourmand/Undo.py
gourmand/__init__.py
gourmand/__main__.py
gourmand/__version__.py
gourmand/batchEditor.py
gourmand/check_encodings.py
gourmand/convert.py
gourmand/gdebug.py
gourmand/gglobals.py
gourmand/i18n.py
gourmand/image_utils.py
gourmand/keymanager.py
gourmand/main.py
gourmand/optionparser.py
gourmand/plugin.py
gourmand/plugin_gui.py
gourmand/plugin_loader.py
gourmand/prefs.py
gourmand/prefsGui.py
gourmand/reccard.py
gourmand/recindex.py
gourmand/recipeIdentifier.py
gourmand/recipeManager.py
gourmand/settings.py
gourmand/shopEditor.py
gourmand/shopgui.py
gourmand/shopping.py
gourmand/sound.py
gourmand/structure.py
gourmand/threadManager.py
gourmand/timeScanner.py
gourmand/timer.py
gourmand/backends/DatabaseChooser.py
gourmand/backends/__init__.py
gourmand/backends/db.py
gourmand/backends/default.db
gourmand/data/ABBREV.txt
gourmand/data/FAQ
gourmand/data/FOOD_DES.txt
gourmand/data/LICENSE
gourmand/data/WEIGHT.txt
gourmand/data/nutritional_data_sr_version
gourmand/data/recipe.dtd
gourmand/data/images/AddToShoppingList.png
gourmand/data/images/Nutrition.png
gourmand/data/images/blue_star.png
gourmand/data/images/gold_star.png
gourmand/data/images/gourmand.ico
gourmand/data/images/gourmand.png
gourmand/data/images/gourmand.svg
gourmand/data/images/half_blue_star.png
gourmand/data/images/half_gold_star.png
gourmand/data/images/no_star.png
gourmand/data/images/reccard.png
gourmand/data/images/reccard_edit.png
gourmand/data/images/splash.png
gourmand/data/images/splash.svg
gourmand/data/locale/af/LC_MESSAGES/gourmand.mo
gourmand/data/locale/ar/LC_MESSAGES/gourmand.mo
gourmand/data/locale/az/LC_MESSAGES/gourmand.mo
gourmand/data/locale/bg/LC_MESSAGES/gourmand.mo
gourmand/data/locale/bs/LC_MESSAGES/gourmand.mo
gourmand/data/locale/ca/LC_MESSAGES/gourmand.mo
gourmand/data/locale/cs/LC_MESSAGES/gourmand.mo
gourmand/data/locale/da/LC_MESSAGES/gourmand.mo
gourmand/data/locale/de/LC_MESSAGES/gourmand.mo
gourmand/data/locale/de_AT/LC_MESSAGES/gourmand.mo
gourmand-1.1.0.dist-info/LICENSE
gourmand-1.1.0.dist-info/METADATA
gourmand-1.1.0.dist-info/WHEEL
gourmand-1.1.0.dist-info/entry_points.txt
gourmand-1.1.0.dist-info/top_level.txt
gourmand-1.1.0.dist-info/RECORD
